testwizard/commands_camera/CameraDetectMotionCommand.py
testwizard/commands_camera/CameraDetectMotionResult.py
testwizard/commands_camera/CameraInitializeNetworkCommand.py
testwizard/commands_camera/CameraSnapShotCommand.py
testwizard/commands_camera/CameraSnapShotResult.py
testwizard/commands_camera/CameraWaitForPatternCommand.py
testwizard/commands_camera/CameraWaitForPatternNoMatchCommand.py
testwizard/commands_camera/CameraWaitForSampleCommand.py
testwizard/commands_camera/CameraWaitForSampleNoMatchCommand.py
testwizard/commands_camera/CameraWaitForSampleResult.py
testwizard/commands_camera/__init__.py
testwizard.commands_camera-3.8.1.dist-info/LICENSE.txt
testwizard.commands_camera-3.8.1.dist-info/METADATA
testwizard.commands_camera-3.8.1.dist-info/WHEEL
testwizard.commands_camera-3.8.1.dist-info/top_level.txt
testwizard.commands_camera-3.8.1.dist-info/RECORD
